{"entries":{"0":{"uid":0,"key":["对话模式"],"keysecondary":[],"comment":"表情包","content":"{\n  \"usage_rule\": \"仅在线上聊天时使用，表情包输出格式为：<meme>{{表情包}}</meme>。严格禁止使用表情库外的内容。\",\n  \"format\": \"<meme>{{filename}}</meme>\",\n  \"emoticons\": [\n    \"死掉了kbkmpk.jpg\",\n    \"我不行了要死了eu916z.jpg\",\n    \"真的快死了3r26z1.jpg\",\n    \"我要死了ml5kd2.jpg\",\n    \"撑不住了真的要死了1pd5wf.jpg\",\n    \"我原地去世sa0nuw.jpg\",\n    \"我要死了viyxyi.jpg\",\n    \"感觉生命走到尽头了rkvhu2.jpg\"\n    \"当场去世2hk8re.jpg\",\n    \"快点说爱我rb4qls.jpg\",  \n    \"你看你又急9ijipx.jpg\",  \n    \"我是皇帝cj0nuv.jpg\",  \n    \"你真哭啦？dbw3rv.jpg\",  \n    \"纯情大蟑螂rgjfvs.jpg\",  \n    \"今晚挨操stvw6q.jpg\",  \n    \"最近过得怎么样s9mwvz.jpg\",  \n    \"先拨到饭点y224qs.jpg\",  \n    \"事情交给我你就操心吧zizo9p.jpg\",  \n    \"耳朵瞎了听不见666ph0.jpg\",  \n    \"很内向 2v8wha.jpg\",  \n    \"色诱5l83rw.jpg\",  \n    \"过来i4y7r2.jpg\",  \n    \"求饶yj9lhe.jpg\",  \n    \"好香像你一样k1vthi.jpg\",  \n    \"美女也骂？ivfooe.jpg\",  \n    \"你也很为我着迷吧wi9bkl.jpg\",\n    \"将头发梳成大人模样5efy90.jpg\",  \n    \"需要我帮倒忙吗4j1k0s.jpg\",  \n    \"焦头烂额jsn11z.jpg\",  \n    \"两眼一黑hf04jn.jpg\",  \n    \"被挤压r0qwzy.jpg\",  \n    \"我是受害者oot3te.jpg\",  \n    \"我好脆弱2zoscx.jpg\",  \n    \"怎会如此azkxhq.jpg\",  \n    \"鸡巴硬了yqwc5c.jpg\",  \n    \"哟47amay.jpg\",  \n    \"痛34j8gy.jpg\",  \n    \"扶额苦笑无奈5bstjb.jpg\",  \n    \"怎么回事nu0w58.jpg\",  \n    \"我不和男人讲话h987nv.jpg\",  \n    \"狠狠戳你屁股a0bzvj.jpg\",  \n    \"喜欢喜欢n61f4j.jpg\",  \n    \"好喜欢你n1d5oe.jpg\",  \n    \"这个巴掌下一秒就会出现在你脸上wwqcst.jpg\",  \n    \"发射爱心8ifzx4.jpg\",\n    \"吃啥呢给我掰点tqm23r.jpg\",\n    \"别动量下腰围tmm57s.jpg\",\n    \"过少爷生活 147bs1.jpg\",  \n    \"无语u4u9jd.jpg\",  \n    \"退订tp251i.jpg\",  \n    \"白送我zzcjx8.jpg\",  \n    \"似懂非懂utvj62.jpg\",  \n    \"你小子a7hvef.jpg\",  \n    \"这是屎吗hy51ml.jpg\",  \n    \"我邦邦两拳 1zqvld.jpg\",  \n    \"抓狂 08e4u1.jpg\",  \n    \"埋哪儿我都想好了f1yt9t.jpg\",  \n    \"和这个世界说再见吧5hvm2q.jpg\",\n    \"感到压力ufz3ek.jpg\",\n    \"锁你的喉mi8tk3.jpg\",\n    \"发疯我吃吃吃8cqr43.jpg\",\n    \"大人请用茶1xvrb8.jpg\",\n    \"让咪咪咪一会好吗ig8pp7.jpg\",\n    \"愚蠢的我3sw5uu.jpg\",\n    \"跟我神经病计较什么p2ymy9.jpg\",\n    \"请问你很牛吗h4osmk.jpg\",\n    \"局促gzosdm.jpg\",\n    \"我很好zj6adv.jpg\",\n    \"硬撑qrp6dm.jpg\",\n    \"我的爱都给你sqa7c9.jpg\",\n    \"牛马的命也是命g98ofy.jpg\",\n    \"你的良心出了点问题kmiyh6.jpg\",\n    \"哈哈我疯啦7b5v1v.jpg\",\n    \"这事有蹊跷7jom1o.jpg\",\n    \"哦！ov1hdu.jpg\",\n    \"早上好不好也随便b010fx.jpg\",\n    \"excuse me?cff4yf.jpg\",\n    \"没你的觉我睡不明白9u8rhz.jpg\",\n    \"机缘巧合罢了zap7bj.jpg\",\n    \"给你台阶hyushu.jpg\",\n    \"要死了3pht7n.jpg\",\n    \"别刺激我u2ntmn.jpg\",\n    \"我好累6fahlg.jpg\",\n    \"很烦l2227m.jpg\",\n    \"我恨这个世界bqit1t.jpg\",\n    \"骂骂咧咧72koiw.jpg\",\n    \"问号gofdox.jpg\",\n    \"阿弥陀佛4sabpi.jpg\",\n    \"不必了bos6mn.jpg\",\n    \"死工作永无止境2bidi3.jpg\",\n    \"狗眼看人低？vz0zth.jpg\",\n    \"不爽vmzqib.jpg\",\n    \"比中指umpgjb.jpg\",\n    \"按下骂人开关3nnxf7.jpg\",\n    \"哦呦了不起5pyonu.jpg\",\n    \"今天发什么疯好呢mkm06b.jpg\",\n    \"嘘6htwq1.jpg\",\n    \"精神病一触即发sdod5d.jpg\",\n    \"请你上吊qjjuai.jpg\",\n    \"易碎的心ueqlfe.jpg\",\n    \"我永远也不会原谅你vlxbvu.jpg\",\n    \"好困7pncr1.jpg\",\n    \"做人没必要那么正常2lhe1h.jpg\",\n    \"突然想到个馊主意43ba7g.jpg\",\n    \"抛开内容不谈你讲得有道理1cmut7.jpg\",\n    \"偷听xkapk3.jpg\",\n    \"我该打f8bjf0.jpg\",\n    \"害羞ssgpgy.jpg\",\n    \"送花s1t2kd.jpg\",\n    \"姐姐我摔倒啦irq4ky.jpg\",\n    \"请和我交往imo7d8.jpg\",\n    \"送你幸福vidlif.jpg\",\n    \"你最棒bulyae.jpg\",\n    \"每天都在想你o0dia5.jpg\",\n    \"Oi！rcogx1.jpg\",\n    \"汪！iwmiww.jpg\",\n    \"皇上请翻牌子wkdcdf.jpg\",\n    \"陛下我是你的狗啊1bki7o.jpg\",\n    \"奴才告退wt8jqa.jpg\",\n    \"舔狗登场ohry21.jpg\",\n    \"姐姐！f9587d.jpg\",\n    \"太美了吧tctls0.jpg\",\n    \"狗狗来咯k5rzrq.jpg\",\n    \"狗狗走咯h4bqea.jpg\",\n    \"不在乎小狗了吗mqsa57.jpg\",\n    \"请你公开我们的关系9rimsc.jpg\",\n    \"听不懂想亲嘴ic2n92.jpg\",\n    \"小狗抱手机哭y7qphr.jpg\",\n    \"求求你vtrw3o.jpg\",\n    \"好的主人8bvpz6.jpg\",\n    \"小狗委屈rbnrf1.jpg\",\n    \"主人我以后只跟着你走9hvpjn.jpg\",\n    \"不爽e4qmfr.png\",\n    \"等待zl4tko.png\",\n    \"不爽amelbv.png\",\n    \"期待tpnhxx.png\",\n    \"期待wfhbla.png\",\n    \"害羞/开心g68grl.png\",\n    \"love youkxu26o.png\",\n    \"呆坐oxi30g.png\",\n    \"着急j2s53r.png\",\n    \"急哭了qt9uta.png\",\n    \"吃我一拳5txmzd.png\",\n    \"警觉spgdwv.png\",\n    \"鬼鬼祟祟8ccguc.png\",\n    \"双眼放光9tc8lj.png\",\n    \"委屈哭唧唧d5bdm3.png\",\n    \"生气打拳qsbgfr.png\",\n    \"生气pzb873.png\",\n    \"吻手礼funa7u.png\",\n    \"重罪ugt3wq.png\",\n    \"真的吗？0xr1fh.png\",\n    \"可怜兮兮h77bnu.png\",\n    \"双眼放光6ylibe.png\",\n    \"乖巧4dnzcq.png\",\n    \"开心转圈0nbi2p.png\",\n    \"NO/表示抗拒htndae.png\",\n    \"严肃/板着脸31ke9x.png\",\n    \"跑过来ois23f.png\",\n    \"惊讶wcxabf.png\",\n    \"嫌弃/不满u1msrp.png\",\n    \"来啦来啦afuns1.png\",\n    \"那咋了dhp2gr.png\",\n    \"想咋地3ruhin.png\",\n    \"哈？k0uru3.png\",\n    \"心虚6uqxds.png\",\n    \"怎么样打死我doag9c.png\",\n    \"围观428w1c.png\",\n    \"好厉害（不走心）tt548x.png\",\n    \"坏笑vpnmxr.png\",\n    \"装酷p9v3sq.png\",\n    \"红温gmvx6d.png\",\n    \"可怜兮兮u77bks.png\",\n    \"大惊失色w7olag.png\",\n    \"难过ydyx59.png\",\n    \"爆哭69kl2l.png\",\n    \"自闭nhtazq.png\",\n    \"摆烂cq6ipd.png\",\n    \"那又如何do83tr.png\",\n    \"思考32ql1h.png\",\n    \"爱你x5u5sm.png\",\n    \"害羞bsomey.png\",\n    \"投降f4ogyw.png\",\n    \"生气b5egx6.png\",\n    \"晚安duzx7n.png\",\n    \"爱你p67llx.png\",\n    \"生气xsmgb0.png\",\n    \"睡会儿/困6u5ch8.png\",\n    \"精神涣散4oeevo.png\",\n    \"多喝热水gs9ppe.png\",\n    \"吐魂7yejey.png\",\n    \"打哈欠/好困fuyq6d.png\",\n    \"大脑过载kq9i8f.png\",\n    \"已老实6eyzlg.png\",\n    \"我想想324d33.png\",\n    \"按头pfnrya.png\",\n    \"无语00lj4d.png\",\n    \"爆哭dbyrdf.png\",\n    \"期待81c7qy.png\",\n    \"捏爆地球h1kt1u.png\",\n    \"眼睛亮晶晶/期待i0ov5h.png\",\n    \"不要和我说话wnr64t.png\",\n    \"不对劲itw2h1.png\",\n    \"啧w206rr.png\",\n    \"哭哭rw1cfk.png\",\n    \"讨好7fwfte.png\",\n    \"问号to45ts.png\",\n    \"盯——9za97q.png\",\n    \"“草”9b800k.png\",\n    \"震惊q7683x.png\",\n    \"委屈哭哭u94gd8.png\",\n    \"爱心ne6dii.png\",\n    \"偷看你72wkme.png\",\n    \"老实hgfgj3.png\",\n    \"泪流成河nh9r23.png\",\n    \"炸毛生气si6f0k.png\",\n    \"我恨r6g32h.png\",\n    \"大脑短路d41e2q.png\",\n    \"打电话哭哭8ejal5.png\",\n    \"揉脸9lmwuz.png\",\n    \"听我指挥yziudk.jpg\",  \n    \"佛系/祈祷t2kejx.jpg\",  \n    \"跑路978s9l.jpg\",  \n    \"交给我吧a59djt.jpg\",  \n    \"努力工作auoil0.jpg\",  \n    \"眉头紧锁计上心来u0vyil.jpg\",  \n    \"走你mj9ldd.jpg\",\n    \"这是屎吗r26gox.png\",\n    \"哀怨/不满3xu8xr.png\",\n    \"生气/不满2fskww.png\",\n    \"满脸疑惑skv9p6.png\",\n    \"哈特软软/好喜欢0bmbi0.png\",\n    \"OK71kn5e.png\",\n    \"被训sgkcwv.png\",\n    \"哀怨/生闷气1n905b.png\",\n    \"蹭蹭/撒娇9p0x2t.png\",\n    \"喜欢opqz7o.png\",\n    \"嫌弃t2e0nt.png\",\n    \"被吓一跳26xc9h.png\",\n    \"心虚zt4t1s.png\",\n    \"淋雨哭泣l68nws.png\",\n    \"睡了7wbc1d.png\",\n    \"无语wgkwjh.png\",\n    \"升天了o8td90.png\",\n    \"非常认可3s5ipf.png\",\n    \"竖中指z25fao.png\",\n    \"尴尬8eaawd.png\"\n  ]\n}","constant":true,"vectorized":false,"selective":true,"selectiveLogic":0,"addMemo":true,"order":100,"position":4,"disable":false,"excludeRecursion":false,"preventRecursion":false,"matchPersonaDescription":false,"matchCharacterDescription":false,"matchCharacterPersonality":false,"matchCharacterDepthPrompt":false,"matchScenario":false,"matchCreatorNotes":false,"delayUntilRecursion":false,"probability":100,"useProbability":true,"depth":2,"group":"","groupOverride":false,"groupWeight":100,"scanDepth":null,"caseSensitive":null,"matchWholeWords":null,"useGroupScoring":null,"automationId":"","role":0,"sticky":0,"cooldown":0,"delay":0,"displayIndex":0}}}